discordemojiparser/__init__.py
discordemojiparser/emoji_enum.py
discordemojiparser/emoji_parser.py
discordemojiparser-1.0.1.dist-info/LICENSE
discordemojiparser-1.0.1.dist-info/METADATA
discordemojiparser-1.0.1.dist-info/WHEEL
discordemojiparser-1.0.1.dist-info/RECORD
